besteffort/__init__.py
besteffort/core.py
besteffort-0.1.1.dist-info/licenses/LICENSE
besteffort-0.1.1.dist-info/METADATA
besteffort-0.1.1.dist-info/WHEEL
besteffort-0.1.1.dist-info/top_level.txt
besteffort-0.1.1.dist-info/RECORD
