Metadata-Version: 2.4
Name: besteffort
Version: 0.1.1
Summary: Best-effort importer and decorator that suppresses exceptions.
Author: Grant Jenks
License-Expression: Apache-2.0
Project-URL: Homepage, https://github.com/grantjenks/python-besteffort
Project-URL: Issue Tracker, https://github.com/grantjenks/python-besteffort/issues
Project-URL: Source Code, https://github.com/grantjenks/python-besteffort
Keywords: import,exceptions,contextlib,resilience
Classifier: Development Status :: 4 - Beta
Classifier: Intended Audience :: Developers
Classifier: Programming Language :: Python
Classifier: Programming Language :: Python :: 3
Classifier: Programming Language :: Python :: 3 :: Only
Classifier: Programming Language :: Python :: 3.10
Classifier: Programming Language :: Python :: 3.11
Classifier: Programming Language :: Python :: 3.12
Classifier: Programming Language :: Python :: 3.13
Classifier: Topic :: Software Development :: Libraries
Classifier: Topic :: Utilities
Requires-Python: >=3.10
License-File: LICENSE
Provides-Extra: dev
Requires-Dist: pytest>=8.0; extra == "dev"
Requires-Dist: nox>=2024.4.15; extra == "dev"
Dynamic: license-file
